setup.py
bin/s3bt
s3bt/__init__.py
s3bt/crypt.py
s3bt/s3bt.py
s3bt/s3bt_crypt.py
s3bt/server.py
s3bt/version.py
s3bt.egg-info/PKG-INFO
s3bt.egg-info/SOURCES.txt
s3bt.egg-info/dependency_links.txt
s3bt.egg-info/not-zip-safe
s3bt.egg-info/requires.txt
s3bt.egg-info/top_level.txt