Metadata-Version: 1.0
Name: s3bt
Version: 1.2.1
Summary: S3-mediated bulk data transfers
Home-page: https://code.stanford.edu/gsb-circle-research/s3bt
Author: W. Ross Morrow
Author-email: gsb_circle_research@stanford.edu
License: MIT
Platform: UNKNOWN
